axiom_trace/__init__.py
axiom_trace/backend.py
axiom_trace/canonical.py
axiom_trace/cli.py
axiom_trace/core.py
axiom_trace/observer.py
axiom_trace/quick.py
axiom_trace/redaction.py
axiom_trace/schema.py
axiom_trace/schemas/axiom_frame_v1_1.json
axiom_trace-1.4.2.dist-info/METADATA
axiom_trace-1.4.2.dist-info/WHEEL
axiom_trace-1.4.2.dist-info/entry_points.txt
axiom_trace-1.4.2.dist-info/RECORD
