Metadata-Version: 2.4
Name: axiom-trace
Version: 1.4.2
Summary: Local-first, append-only trace vault for AI agents with cryptographic integrity
Author: Axiom Team
License-Expression: MIT
Keywords: accountability,ai,memvid,tracing,vector-search
Classifier: Development Status :: 4 - Beta
Classifier: Intended Audience :: Developers
Classifier: License :: OSI Approved :: MIT License
Classifier: Programming Language :: Python :: 3
Classifier: Programming Language :: Python :: 3.9
Classifier: Programming Language :: Python :: 3.10
Classifier: Programming Language :: Python :: 3.11
Classifier: Programming Language :: Python :: 3.12
Requires-Python: >=3.9
Requires-Dist: filelock>=3.12.0
Requires-Dist: jsonschema==4.22.0
Requires-Dist: memvid==0.1.3
Requires-Dist: orjson==3.10.7
Requires-Dist: python-dotenv>=1.0.0
Requires-Dist: typer==0.12.3
Provides-Extra: dev
Requires-Dist: pytest-cov>=4.1.0; extra == 'dev'
Requires-Dist: pytest>=7.4.0; extra == 'dev'
